LICENSE
README.md
setup.py
aiwang_indicator/__init__.py
aiwang_indicator/context.py
aiwang_indicator.egg-info/PKG-INFO
aiwang_indicator.egg-info/SOURCES.txt
aiwang_indicator.egg-info/dependency_links.txt
aiwang_indicator.egg-info/requires.txt
aiwang_indicator.egg-info/top_level.txt
aiwang_indicator/data/__init__.py
aiwang_indicator/data/data_api.py
aiwang_indicator/data/loader/__init__.py
aiwang_indicator/data/loader/ak_loader.py
aiwang_indicator/data/loader/base_loader.py
aiwang_indicator/indicator/__init__.py
aiwang_indicator/indicator/decorators.py
aiwang_indicator/indicator/indicator.py
aiwang_indicator/model/__init__.py
aiwang_indicator/model/series.py